{
	"_comment": "SPEC v5 §2 — Ashveil Isle. x/y are PIXELS in the artwork (1672x941), measured by a pixel scan of the DRAWN grid lines. The grid is deliberately NOT uniform (AI artwork), hence real line positions instead of a formula.",
	"image": "res://assets/textures/worldmap.png",
	"image_size": [1672, 941],
	"grid": {
		"rows": ["A", "B", "C", "D", "E", "F"],
		"cols": ["1", "2", "3", "4", "5", "6", "7", "8", "9", "10"],
		"x": [75, 237, 396, 556, 710, 874, 1031, 1178, 1331, 1478, 1625],
		"y": [107, 228, 347, 469, 591, 710, 838]
	},
	"start_sector": "F4",
	"default_lock": "Locked in the demo.",
	"_deploy_rule": "Deployment ALWAYS goes to the sector the squad currently stands in (Game.sector). 'demo' only means: part of the demo content — NOT: directly selectable. You move on by foot across the sector edge (SPEC v5 §2: start F4, only exit west -> F3). island.gd accepts 'demo' and 'playable' as equivalent.",
	"sectors": [
		{"id": "F4", "name": "Landing Zone", "status": "demo", "exits": ["F3"],
		 "note": "Insertion point. The helicopter sets you down here."},
		{"id": "F3", "name": "Rookhaven", "status": "demo", "exits": ["F4"],
		 "note": "Fishing village under Helix guard. Tobias Rook is held in the warehouse cellar.",
		 "reach": "No direct insertion — leave the landing zone to the west on foot."},
		{"id": "F2", "name": "Rookhaven — Docks", "status": "locked",
		 "note": "The far end of the village. Sealed off for the demo."},
		{"id": "E4", "name": "Mined Ridge", "status": "locked",
		 "note": "The ridge north is mined. Helix exclusion zone."},
		{"id": "C3", "name": "Briar Hollow", "status": "locked",
		 "note": "Second village, loyalty questline. Not in the demo."},
		{"id": "C4", "name": "Briar Hollow", "status": "locked",
		 "note": "Second village, loyalty questline. Not in the demo."},
		{"id": "E6", "name": "Widow's Vein Diamond Mine", "status": "locked",
		 "note": "Diamonds. This is what pays for the Helix. Not in the demo."},
		{"id": "A5", "name": "Stoneglint Diamond Mine", "status": "locked",
		 "note": "Diamonds. This is what pays for the Helix. Not in the demo."},
		{"id": "B5", "name": "Stoneglint Diamond Mine", "status": "locked",
		 "note": "Diamonds. This is what pays for the Helix. Not in the demo."},
		{"id": "C7", "name": "Hollowpoint Barracks", "status": "locked",
		 "note": "Helix garrison. Not in the demo."},
		{"id": "C8", "name": "Hollowpoint Barracks", "status": "locked",
		 "note": "Helix garrison. Not in the demo."},
		{"id": "D7", "name": "Hollowpoint Barracks", "status": "locked",
		 "note": "Helix garrison. Not in the demo."},
		{"id": "D8", "name": "Hollowpoint Barracks", "status": "locked",
		 "note": "Helix garrison. Not in the demo."},
		{"id": "B9", "name": "Manor Causeway", "status": "locked",
		 "note": "The causeway out to the rock island."},
		{"id": "A9", "name": "Helix Manor", "status": "locked",
		 "note": "Corporate seat of Helix Bioscience. The finale — not in the demo."},
		{"id": "A10", "name": "Helix Manor", "status": "locked",
		 "note": "Corporate seat of Helix Bioscience. The finale — not in the demo."},
		{"id": "B10", "name": "Helix Manor", "status": "locked",
		 "note": "Corporate seat of Helix Bioscience. The finale — not in the demo."}
	]
}
